directory_info_extractor/__init__.py
directory_info_extractor/extractor.py
directory_info_extractor-0.1.1.dist-info/LICENSE
directory_info_extractor-0.1.1.dist-info/METADATA
directory_info_extractor-0.1.1.dist-info/WHEEL
directory_info_extractor-0.1.1.dist-info/top_level.txt
directory_info_extractor-0.1.1.dist-info/RECORD
