Metadata-Version: 2.1
Name: directory-info-extractor
Version: 0.1.1
Summary: A lightweight Python library for extracting comprehensive information from directories
Home-page: https://github.com/ezequielsobrino/directory-info-extractor
Author: Ezequiel Sobrino
Classifier: Development Status :: 3 - Alpha
Classifier: Intended Audience :: Developers
Classifier: License :: OSI Approved :: MIT License
Classifier: Operating System :: OS Independent
Classifier: Programming Language :: Python :: 3.8
Classifier: Programming Language :: Python :: 3.9
Classifier: Programming Language :: Python :: 3.10
Classifier: Programming Language :: Python :: 3.11
Classifier: Programming Language :: Python :: 3.12
Requires-Python: >=3.8
License-File: LICENSE
